{
	"info": {
		"_postman_id": "4f4f1804-c853-490d-b03c-80e2d545bb0c",
		"name": "BPDM Cleaning Service Dummy",
		"description": "Place holder for the cleaning service provider",
		"schema": "https://schema.getpostman.com/json/collection/v2.1.0/collection.json",
		"_exporter_id": "26818013"
	},
	"item": [
		{
			"name": "New Request",
			"request": {
				"method": "GET",
				"header": []
			},
			"response": []
		}
	],
	"variable": [
		{
			"key": "baseUrl",
			"value": "http://localhost:8084"
		}
	]
}